mikeio/__init__.py
mikeio/_interpolation.py
mikeio/_spectral.py
mikeio/_time.py
mikeio/_track.py
mikeio/exceptions.py
mikeio/generic.py
mikeio/py.typed
mikeio/dataset/__init__.py
mikeio/dataset/_data_plot.py
mikeio/dataset/_data_utils.py
mikeio/dataset/_dataarray.py
mikeio/dataset/_dataset.py
mikeio/dfs/__init__.py
mikeio/dfs/_dfs.py
mikeio/dfs/_dfs0.py
mikeio/dfs/_dfs1.py
mikeio/dfs/_dfs2.py
mikeio/dfs/_dfs3.py
mikeio/dfsu/__init__.py
mikeio/dfsu/_common.py
mikeio/dfsu/_dfsu.py
mikeio/dfsu/_factory.py
mikeio/dfsu/_layered.py
mikeio/dfsu/_mesh.py
mikeio/dfsu/_spectral.py
mikeio/eum/__init__.py
mikeio/eum/_eum.py
mikeio/pfs/__init__.py
mikeio/pfs/_pfsdocument.py
mikeio/pfs/_pfssection.py
mikeio/spatial/_FM_geometry.py
mikeio/spatial/_FM_geometry_layered.py
mikeio/spatial/_FM_geometry_spectral.py
mikeio/spatial/_FM_utils.py
mikeio/spatial/__init__.py
mikeio/spatial/_geometry.py
mikeio/spatial/_grid_geometry.py
mikeio/spatial/_utils.py
mikeio/spatial/crs.py
mikeio-2.5.0.dist-info/METADATA
mikeio-2.5.0.dist-info/WHEEL
mikeio-2.5.0.dist-info/RECORD
