Metadata-Version: 2.4
Name: mikeio
Version: 2.5.0
Summary: A package that uses the DHI dfs libraries to create, write and read dfs and mesh files.
Project-URL: Homepage, https://github.com/DHI/mikeio
Project-URL: Bug Tracker, https://github.com/DHI/mikeio/issues
Author-email: Henrik Andersson <jan@dhigroup.com>, Jesper Sandvig Mariegaard <jem@dhigroup.com>
License-Expression: BSD-3-Clause
Classifier: Development Status :: 5 - Production/Stable
Classifier: Intended Audience :: Science/Research
Classifier: License :: OSI Approved :: BSD License
Classifier: Programming Language :: Python
Classifier: Programming Language :: Python :: 3
Classifier: Programming Language :: Python :: 3.10
Classifier: Programming Language :: Python :: 3.11
Classifier: Programming Language :: Python :: 3.12
Classifier: Programming Language :: Python :: 3.13
Classifier: Topic :: Scientific/Engineering
Requires-Python: >=3.10
Requires-Dist: matplotlib>=3.6.0
Requires-Dist: mikecore>=0.2.1
Requires-Dist: numpy>=1.22.0
Requires-Dist: pandas>=1.3
Requires-Dist: pyyaml
Requires-Dist: scipy>=1.0
Requires-Dist: tqdm
Requires-Dist: typing-extensions
Requires-Dist: xarray
Provides-Extra: dev
Requires-Dist: mypy==1.11.1; extra == 'dev'
Requires-Dist: netcdf4; extra == 'dev'
Requires-Dist: polars; extra == 'dev'
Requires-Dist: pyproj; extra == 'dev'
Requires-Dist: pytest; extra == 'dev'
Requires-Dist: quarto-cli; extra == 'dev'
Requires-Dist: quartodoc==0.9.1; extra == 'dev'
Requires-Dist: rasterio; extra == 'dev'
Requires-Dist: ruff==0.6.2; extra == 'dev'
Requires-Dist: shapely; extra == 'dev'
Requires-Dist: xarray; extra == 'dev'
Provides-Extra: notebooks
Requires-Dist: folium; extra == 'notebooks'
Requires-Dist: geopandas; extra == 'notebooks'
Requires-Dist: jupyter; extra == 'notebooks'
Requires-Dist: mapclassify; extra == 'notebooks'
Requires-Dist: matplotlib; extra == 'notebooks'
Requires-Dist: nbconvert; extra == 'notebooks'
Requires-Dist: nbformat; extra == 'notebooks'
Requires-Dist: netcdf4; extra == 'notebooks'
Requires-Dist: rasterio; extra == 'notebooks'
Requires-Dist: scikit-learn; extra == 'notebooks'
Requires-Dist: xarray; extra == 'notebooks'
Provides-Extra: test
Requires-Dist: mypy==1.11.1; extra == 'test'
Requires-Dist: polars; extra == 'test'
Requires-Dist: pyproj; extra == 'test'
Requires-Dist: pytest; extra == 'test'
Requires-Dist: pytest-cov; extra == 'test'
Requires-Dist: shapely; extra == 'test'
Requires-Dist: xarray; extra == 'test'
